test_setup.py
getfx/__init__.py
getfx/__main__.py
getfx/cmdparser.py
getfx/getfx.py
getfx/getfxnbp.py
getfx-0.1.8.dist-info/LICENSE
getfx-0.1.8.dist-info/METADATA
getfx-0.1.8.dist-info/WHEEL
getfx-0.1.8.dist-info/entry_points.txt
getfx-0.1.8.dist-info/top_level.txt
getfx-0.1.8.dist-info/RECORD
