Metadata-Version: 2.1
Name: getfx
Version: 0.1.8
Summary: Get FX is tool to retrieve average FX rates from NBP
Author: Kamil Niklasinski
Author-email: kamil.niklasinski@gmail.com
License: Apache 2
Project-URL: Issue tracker, https://github.com/kniklas/get-fx/issues
Project-URL: Documentation, https://kniklas.github.io/get-fx/
Project-URL: Source, https://github.com/kniklas/get-fx
Keywords: NBP API FX
Platform: any
Classifier: Development Status :: 3 - Alpha
Classifier: Environment :: Console
Classifier: Intended Audience :: Financial and Insurance Industry
Classifier: License :: OSI Approved :: Apache Software License
Classifier: Natural Language :: English
Classifier: Operating System :: OS Independent
Classifier: Programming Language :: Python :: 3
Requires-Python: >=3.7
License-File: LICENSE
Requires-Dist: requests
